setup.cfg
setup.py
daftpunk.egg-info/PKG-INFO
daftpunk.egg-info/SOURCES.txt
daftpunk.egg-info/dependency_links.txt
daftpunk.egg-info/requires.txt
daftpunk.egg-info/top_level.txt
dp2/__init__.py
dp2/client.py