Metadata-Version: 1.1
Name: daftpunk
Version: 0.3
Summary: Scrape & process data from daft.ie
Home-page: https://github.com/nicr9/daftpunk
Author: Nic Roland
Author-email: nicroland9@gmail.com
License: MIT
Download-URL: https://github.com/nicr9/daftpunk/tarball/v0.3
Platform: UNKNOWN
